Metadata-Version: 1.0
Name: das-statistics
Version: 0.1
Summary: Statistical Distributions
Home-page: UNKNOWN
Author: Sudip Das
Author-email: sudip1012@yahoo.com
License: UNKNOWN
Platform: UNKNOWN
